paraglidetranslator/__init__.py
paraglidetranslator/components/Translate.py
paraglidetranslator/components/__init__.py
paraglidetranslator/components/deepl_key.py
paraglidetranslator/components/deeplconnection.py
paraglidetranslator/components/langeditor.py
paraglidetranslator/components/open_dialog.py
paraglidetranslator/components/singleton.py
paraglidetranslator/images/translator.icns
paraglidetranslator/images/translator.ico
paraglidetranslator/images/translator.png
paraglidetranslator/main.py
paraglidetranslator-0.1.0.dist-info/METADATA
paraglidetranslator-0.1.0.dist-info/WHEEL
paraglidetranslator-0.1.0.dist-info/entry_points.txt
paraglidetranslator-0.1.0.dist-info/RECORD
