Metadata-Version: 2.1
Name: paraglidetranslator
Version: 0.1.0
Summary: Translator for Paraglide JSONS based on DeepL API
Author: Lukas Rosenthaler
Author-email: lukas.rosenthaler@unibas.ch
Requires-Python: >=3.12,<4.0
Classifier: Programming Language :: Python :: 3
Classifier: Programming Language :: Python :: 3.12
Requires-Dist: deepl (>=1.21.0,<2.0.0)
Requires-Dist: pyobjc (>=11.0,<12.0)
